LICENSE.txt
MANIFEST.in
README.rst
pysketch
setup.cfg
setup.py
src/pysketch/__init__.py
src/pysketch.egg-info/PKG-INFO
src/pysketch.egg-info/SOURCES.txt
src/pysketch.egg-info/dependency_links.txt
src/pysketch.egg-info/top_level.txt
src/pysketch/pygobject/__init__.py
src/pysketch/pygobject/gui.py
src/pysketch/pygtk/__init__.py
src/pysketch/pygtk/gui.py
src/pysketch/pyqt4/__init__.py
src/pysketch/pyqt4/gui.py
src/pysketch/tkinter/__init__.py
src/pysketch/tkinter/gui.py