Metadata-Version: 1.1
Name: pysketch
Version: 1.2
Summary: Draw simple notes and scribbles on a canvas
Home-page: https://bitbucket.org/dirkbaechle/pysketch
Author: Dirk Baechle
Author-email: dl9obn@darc.de
License: MIT
Keywords: desktop note scribble
Platform: UNKNOWN
Classifier: Development Status :: 3 - Alpha
Classifier: Environment :: X11 Applications
Classifier: Intended Audience :: End Users/Desktop
Classifier: Topic :: Utilities
Classifier: License :: OSI Approved :: MIT License
Classifier: Programming Language :: Python :: 2
